class:com/vmlens/api/AllInterleavings
method:<init>(Ljava/lang/String;)V
  ALOAD_0
  ALOAD_1
  ICONST_0
  INVOKESPECIAL  com/vmlens/api/AllInterleavings.<init>:(Ljava/lang/String;Z)V
  RETURN
method:<init>(Ljava/lang/String;Z)V
  ALOAD_0
  ALOAD_1
  ILOAD_2
  BIPUSH
  BIPUSH
  SIPUSH
  SIPUSH
  SIPUSH
  NEW  java/util/LinkedList
  DUP
  INVOKESPECIAL  java/util/LinkedList.<init>:()V
  INVOKESPECIAL  com/vmlens/api/AllInterleavings.<init>:(Ljava/lang/String;ZIIIIILjava/util/List;)V
  RETURN
method:<init>(Ljava/lang/String;ZIIIIILjava/util/List;)V
  ALOAD_0
  INVOKESPECIAL  java/lang/Object.<init>:()V
  ALOAD_0
  ALOAD_1
  PUTFIELD  com/vmlens/api/AllInterleavings.name:Ljava/lang/String;
  ALOAD_0
  ILOAD_2
  PUTFIELD  com/vmlens/api/AllInterleavings.throwExceptionWhenNoAgent:Z
  ALOAD_0
  ILOAD_3
  PUTFIELD  com/vmlens/api/AllInterleavings.maximumIterations:I
  ALOAD_0
  ILOAD_4
  PUTFIELD  com/vmlens/api/AllInterleavings.maximumAlternatingOrders:I
  ALOAD_0
  ILOAD_5
  PUTFIELD  com/vmlens/api/AllInterleavings.synchronizationActionsLoopThreshold:I
  ALOAD_0
  ILOAD_6
  PUTFIELD  com/vmlens/api/AllInterleavings.unsynchronizedOperationsLoopThreshold:I
  ALOAD_0
  ILOAD_7
  PUTFIELD  com/vmlens/api/AllInterleavings.reportAsSummaryThreshold:I
  ALOAD_0
  ALOAD_8
  PUTFIELD  com/vmlens/api/AllInterleavings.intentionalDataRaces:Ljava/util/List;
  RETURN
method:hasNext()Z
  ALOAD_0
  ALOAD_0
  INVOKESTATIC  com/vmlens/transformed/agent/bootstrap/callback/VmlensApiCallback.hasNext:(Ljava/lang/Object;)Z
  IRETURN
method:next()Lcom/vmlens/api/Interleaving;
  NEW  com/vmlens/api/Interleaving
  DUP
  ALOAD_0
  GETFIELD  com/vmlens/api/AllInterleavings.index:I
  INVOKESPECIAL  com/vmlens/api/Interleaving.<init>:(I)V
  ASTORE_1
  ALOAD_0
  DUP
  GETFIELD  com/vmlens/api/AllInterleavings.index:I
  ICONST_1
  IADD
  PUTFIELD  com/vmlens/api/AllInterleavings.index:I
  ALOAD_1
  ARETURN
method:close()V
  ALOAD_0
  ALOAD_0
  INVOKESTATIC  com/vmlens/transformed/agent/bootstrap/callback/VmlensApiCallback.close:(Ljava/lang/Object;)V
  RETURN
method:hasNext(Ljava/lang/Object;)Z
  ALOAD_0
  GETFIELD  com/vmlens/api/AllInterleavings.throwExceptionWhenNoAgent:Z
  IFEQ
  NEW  java/lang/RuntimeException
  DUP
  load:The vmlens java agent is not configured. See https://vmlens.com/docs/ for configuring the vmlens java agent.
  INVOKESPECIAL  java/lang/RuntimeException.<init>:(Ljava/lang/String;)V
  ATHROW
  GETSTATIC  java/lang/System.err:Ljava/io/PrintStream;
  load:The vmlens java agent is not configured.
  INVOKEVIRTUAL  java/io/PrintStream.println:(Ljava/lang/String;)V
  GETSTATIC  java/lang/System.err:Ljava/io/PrintStream;
  load:See https://vmlens.com/docs/ for configuring the vmlens java agent.
  INVOKEVIRTUAL  java/io/PrintStream.println:(Ljava/lang/String;)V
  ICONST_0
  IRETURN
method:close(Ljava/lang/Object;)V
  RETURN
method:iterator()Ljava/util/Iterator;
  ALOAD_0
  ARETURN
method:next()Ljava/lang/Object;
  ALOAD_0
  INVOKEVIRTUAL  com/vmlens/api/AllInterleavings.next:()Lcom/vmlens/api/Interleaving;
  ARETURN