// class version 51.0 (51)
// access flags 0x21
public class com/vmlens/api/AllInterleavings implements java/lang/AutoCloseable {

  // compiled from: AllInterleavings.java

  // access flags 0x4A
  private static volatile Lcom/vmlens/api/LogLevel; logLevel

  // access flags 0x11
  public final Ljava/lang/String; name

  // access flags 0x11
  public final Z showStatementsWhenSingleThreaded

  // access flags 0x11
  public final Z showStatementsInExecutor

  // access flags 0x11
  public final Z showNonVolatileSharedMemoryAccess

  // access flags 0x11
  public final I maximumRuns

  // access flags 0x11
  public final I maximumSynchronizationActionsPerThread

  // access flags 0x11
  public final [Ljava/lang/Class; removeAtomicAnnotationFromClassArray

  // access flags 0x1
  public <init>(Ljava/lang/String;)V
   L0
    LINENUMBER 90 L0
    ALOAD 0
    ALOAD 1
    ICONST_0
    ICONST_0
    ICONST_0
    SIPUSH 5000
    SIPUSH 2000
    ICONST_0
    ANEWARRAY java/lang/Class
    INVOKESPECIAL com/vmlens/api/AllInterleavings.<init> (Ljava/lang/String;ZZZII[Ljava/lang/Class;)V
   L1
    LINENUMBER 91 L1
    RETURN
   L2
    LOCALVARIABLE this Lcom/vmlens/api/AllInterleavings; L0 L2 0
    LOCALVARIABLE name Ljava/lang/String; L0 L2 1
    MAXSTACK = 8
    MAXLOCALS = 2

  // access flags 0x9
  public static logLevel()Lcom/vmlens/api/LogLevel;
   L0
    LINENUMBER 95 L0
    GETSTATIC com/vmlens/api/AllInterleavings.logLevel : Lcom/vmlens/api/LogLevel;
    ARETURN
    MAXSTACK = 1
    MAXLOCALS = 0

  // access flags 0x9
  public static setLogLevel(Lcom/vmlens/api/LogLevel;)V
   L0
    LINENUMBER 99 L0
    ALOAD 0
    PUTSTATIC com/vmlens/api/AllInterleavings.logLevel : Lcom/vmlens/api/LogLevel;
   L1
    LINENUMBER 100 L1
    RETURN
   L2
    LOCALVARIABLE logLevel Lcom/vmlens/api/LogLevel; L0 L2 0
    MAXSTACK = 1
    MAXLOCALS = 1

  // access flags 0x0
  <init>(Ljava/lang/String;ZZZII[Ljava/lang/Class;)V
   L0
    LINENUMBER 104 L0
    ALOAD 0
    INVOKESPECIAL java/lang/Object.<init> ()V
   L1
    LINENUMBER 105 L1
    ALOAD 0
    ALOAD 1
    PUTFIELD com/vmlens/api/AllInterleavings.name : Ljava/lang/String;
   L2
    LINENUMBER 106 L2
    ALOAD 0
    ILOAD 2
    PUTFIELD com/vmlens/api/AllInterleavings.showStatementsWhenSingleThreaded : Z
   L3
    LINENUMBER 107 L3
    ALOAD 0
    ILOAD 3
    PUTFIELD com/vmlens/api/AllInterleavings.showStatementsInExecutor : Z
   L4
    LINENUMBER 108 L4
    ALOAD 0
    ILOAD 4
    PUTFIELD com/vmlens/api/AllInterleavings.showNonVolatileSharedMemoryAccess : Z
   L5
    LINENUMBER 109 L5
    ALOAD 0
    ILOAD 5
    PUTFIELD com/vmlens/api/AllInterleavings.maximumRuns : I
   L6
    LINENUMBER 110 L6
    ALOAD 0
    ILOAD 6
    PUTFIELD com/vmlens/api/AllInterleavings.maximumSynchronizationActionsPerThread : I
   L7
    LINENUMBER 111 L7
    ALOAD 0
    ALOAD 7
    PUTFIELD com/vmlens/api/AllInterleavings.removeAtomicAnnotationFromClassArray : [Ljava/lang/Class;
   L8
    LINENUMBER 112 L8
    RETURN
   L9
    LOCALVARIABLE this Lcom/vmlens/api/AllInterleavings; L0 L9 0
    LOCALVARIABLE name Ljava/lang/String; L0 L9 1
    LOCALVARIABLE showStatementsWhenSingleThreaded Z L0 L9 2
    LOCALVARIABLE showStatementsInExecutor Z L0 L9 3
    LOCALVARIABLE showNonVolatileSharedMemoryAccess Z L0 L9 4
    LOCALVARIABLE maximum_run_count I L0 L9 5
    LOCALVARIABLE maximum_operation_per_thread_count I L0 L9 6
    LOCALVARIABLE testClassArray [Ljava/lang/Class; L0 L9 7
    MAXSTACK = 2
    MAXLOCALS = 8

  // access flags 0x9
  public static builder(Ljava/lang/String;)Lcom/vmlens/api/AllInterleavingsBuilder;
   L0
    LINENUMBER 126 L0
    NEW com/vmlens/api/AllInterleavingsBuilder
    DUP
    ALOAD 0
    INVOKESPECIAL com/vmlens/api/AllInterleavingsBuilder.<init> (Ljava/lang/String;)V
    ARETURN
   L1
    LOCALVARIABLE name Ljava/lang/String; L0 L1 0
    MAXSTACK = 3
    MAXLOCALS = 1

  // access flags 0x1
  public hasNext()Z
   L0
    LINENUMBER 139 L0
    ALOAD 0
    INVOKESTATIC com/vmlens/trace/agent/bootstrap/callback/VmlensApiCallback.hasNext (Ljava/lang/Object;)Z
    IRETURN
   L1
    LOCALVARIABLE this Lcom/vmlens/api/AllInterleavings; L0 L1 0
    MAXSTACK = 1
    MAXLOCALS = 1

  // access flags 0x1
  public close()V
   L0
    LINENUMBER 149 L0
    ALOAD 0
    INVOKESTATIC com/vmlens/trace/agent/bootstrap/callback/VmlensApiCallback.close (Ljava/lang/Object;)V
   L1
    LINENUMBER 150 L1
    RETURN
   L2
    LOCALVARIABLE this Lcom/vmlens/api/AllInterleavings; L0 L2 0
    MAXSTACK = 1
    MAXLOCALS = 1

  // access flags 0xA
  private static hasNext(Ljava/lang/Object;)Z
   L0
    LINENUMBER 156 L0
    ICONST_0
    IRETURN
   L1
    LOCALVARIABLE object Ljava/lang/Object; L0 L1 0
    MAXSTACK = 1
    MAXLOCALS = 1

  // access flags 0xA
  private static close(Ljava/lang/Object;)V
   L0
    LINENUMBER 162 L0
    RETURN
   L1
    LOCALVARIABLE obj Ljava/lang/Object; L0 L1 0
    MAXSTACK = 0
    MAXLOCALS = 1

  // access flags 0x8
  static <clinit>()V
   L0
    LINENUMBER 32 L0
    GETSTATIC com/vmlens/api/LogLevel.INFO : Lcom/vmlens/api/LogLevel;
    PUTSTATIC com/vmlens/api/AllInterleavings.logLevel : Lcom/vmlens/api/LogLevel;
    RETURN
    MAXSTACK = 1
    MAXLOCALS = 0
}